LICENSE
MANIFEST.in
README.rst
setup.cfg
setup.py
django_admin_nmb.egg-info/PKG-INFO
django_admin_nmb.egg-info/SOURCES.txt
django_admin_nmb.egg-info/dependency_links.txt
django_admin_nmb.egg-info/top_level.txt
docs/images/SCR1.PNG
docs/images/SCR2.PNG
docs/images/SCR3.PNG
docs/images/SCR4.PNG
no_more_blue/__init__.py
no_more_blue/apps.py
no_more_blue/urls.py
no_more_blue/views.py
no_more_blue/static/admin/css_apple/autocomplete.css
no_more_blue/static/admin/css_apple/base.css
no_more_blue/static/admin/css_apple/changelists.css
no_more_blue/static/admin/css_apple/forms.css
no_more_blue/static/admin/css_apple/login.css
no_more_blue/static/admin/css_apple/nav_sidebar.css
no_more_blue/static/admin/css_apple/widgets.css
no_more_blue/static/admin/css_apple/vendor/select2/select2.css
no_more_blue/static/admin/css_apple/vendor/select2/select2.min.css
no_more_blue/static/admin/css_base/autocomplete.css
no_more_blue/static/admin/css_base/base.css
no_more_blue/static/admin/css_base/changelists.css
no_more_blue/static/admin/css_base/forms.css
no_more_blue/static/admin/css_base/login.css
no_more_blue/static/admin/css_base/nav_sidebar.css
no_more_blue/static/admin/css_base/widgets.css
no_more_blue/static/admin/css_base/vendor/select2/LICENSE-SELECT2.md
no_more_blue/static/admin/css_base/vendor/select2/select2.css
no_more_blue/static/admin/css_base/vendor/select2/select2.min.css
no_more_blue/static/admin/css_blueberry/autocomplete.css
no_more_blue/static/admin/css_blueberry/base.css
no_more_blue/static/admin/css_blueberry/changelists.css
no_more_blue/static/admin/css_blueberry/forms.css
no_more_blue/static/admin/css_blueberry/login.css
no_more_blue/static/admin/css_blueberry/nav_sidebar.css
no_more_blue/static/admin/css_blueberry/widgets.css
no_more_blue/static/admin/css_blueberry/vendor/select2/select2.css
no_more_blue/static/admin/css_blueberry/vendor/select2/select2.min.css
no_more_blue/static/admin/css_grapes/autocomplete.css
no_more_blue/static/admin/css_grapes/base.css
no_more_blue/static/admin/css_grapes/changelists.css
no_more_blue/static/admin/css_grapes/forms.css
no_more_blue/static/admin/css_grapes/login.css
