Metadata-Version: 1.1
Name: django-admin-nmb
Version: 0.2.1
Summary: A Django Admin skin that can be set for the entire project or for each session.
Home-page: https://github.com/CoLuiza/django-admin-no-more-blue
Author: Luiza-Mihaela Coman
Author-email: lmcdidi@gmail.com
License: BSD-2-Clause-FreeBSD
Platform: UNKNOWN
Classifier: Environment :: Web Environment
Classifier: Framework :: Django
Classifier: Framework :: Django :: 3.1
Classifier: Intended Audience :: Developers
Classifier: License :: OSI Approved :: BSD License
Classifier: Operating System :: OS Independent
Classifier: Programming Language :: Python
Classifier: Programming Language :: Python :: 3
Classifier: Programming Language :: Python :: 3 :: Only
Classifier: Programming Language :: Python :: 3.6
Classifier: Programming Language :: Python :: 3.7
Classifier: Programming Language :: Python :: 3.8
Classifier: Topic :: Internet :: WWW/HTTP
Classifier: Topic :: Internet :: WWW/HTTP :: Dynamic Content
